pykd/DbgModel.dll
pykd/__init__.py
pykd/dbgeng.dll
pykd/dbghelp.dll
pykd/msdia140.dll
pykd/pykd.pyd
pykd/srcsrv.dll
pykd/symsrv.dll
pykd-0.3.4.15.dist-info/METADATA
pykd-0.3.4.15.dist-info/WHEEL
pykd-0.3.4.15.dist-info/top_level.txt
pykd-0.3.4.15.dist-info/RECORD
