Metadata-Version: 2.1
Name: pykd
Version: 0.3.4.15
Summary: python windbg extension
Home-page: UNKNOWN
Author: UNKNOWN
Author-email: UNKNOWN
License: UNKNOWN
Platform: UNKNOWN
